odoo/addons/maintenance_equipment_custom_info/README.rst
odoo/addons/maintenance_equipment_custom_info/__init__.py
odoo/addons/maintenance_equipment_custom_info/__manifest__.py
odoo/addons/maintenance_equipment_custom_info/demo/custom.info.category.csv
odoo/addons/maintenance_equipment_custom_info/demo/custom.info.option.csv
odoo/addons/maintenance_equipment_custom_info/demo/custom.info.property.csv
odoo/addons/maintenance_equipment_custom_info/demo/custom.info.template.csv
odoo/addons/maintenance_equipment_custom_info/demo/defaults.xml
odoo/addons/maintenance_equipment_custom_info/demo/res_groups.xml
odoo/addons/maintenance_equipment_custom_info/i18n/es.po
odoo/addons/maintenance_equipment_custom_info/i18n/it.po
odoo/addons/maintenance_equipment_custom_info/i18n/maintenance_equipment_custom_info.pot
odoo/addons/maintenance_equipment_custom_info/i18n/pt_BR.po
odoo/addons/maintenance_equipment_custom_info/models/__init__.py
odoo/addons/maintenance_equipment_custom_info/models/maintenance_equipment.py
odoo/addons/maintenance_equipment_custom_info/readme/CONTRIBUTORS.rst
odoo/addons/maintenance_equipment_custom_info/readme/DESCRIPTION.rst
odoo/addons/maintenance_equipment_custom_info/readme/USAGE.rst
odoo/addons/maintenance_equipment_custom_info/security/maintenance_equipment_custom_info_security.xml
odoo/addons/maintenance_equipment_custom_info/static/description/icon.png
odoo/addons/maintenance_equipment_custom_info/static/description/index.html
odoo/addons/maintenance_equipment_custom_info/views/maintenance_equipment_views.xml
odoo13_addon_maintenance_equipment_custom_info-13.0.1.0.1.dev10.dist-info/METADATA
odoo13_addon_maintenance_equipment_custom_info-13.0.1.0.1.dev10.dist-info/WHEEL
odoo13_addon_maintenance_equipment_custom_info-13.0.1.0.1.dev10.dist-info/top_level.txt
odoo13_addon_maintenance_equipment_custom_info-13.0.1.0.1.dev10.dist-info/RECORD
